[
  {
    "name": "admin",
    "score": "0",
    "available": "false",
    "song": "Solid Roots AIO"
  },
  {
    "name": "Ryan Welsh",
    "score": "85449",
    "available": "true",
    "song": "Solid Roots AIO"
  },
  {
    "name": "Shawn Markley",
    "score": "85494",
    "available": "true",
    "song": "IWF AIO"
  },
  {
    "name": "Rebecca Cannon",
    "score": "89546",
    "available": "true",
    "song": "Solid Roots AIO"
  },
  {
    "name": "KAtie Welsh",
    "score": "81665",
    "available": "false",
    "song": "Solid Roots AIO"
  },
  {
    "name": "James Hedgepath",
    "score": "83466",
    "available": "false",
    "song": "Solid Roots AIO"
  },
  {
    "name": "Ray Tarroll",
    "score": "72300",
    "available": "false",
    "song": "Solid Roots AIO"
  },
  {
    "name": "Marydean Czach",
    "score": "80257",
    "available": "false",
    "song": "IWF AIO"
  },
  {
    "name": "Ashley Belle",
    "score": "62307",
    "available": "false",
    "song": "Solid Roots AIO"
  },
  {
    "name": "Irene Trantas",
    "score": "54570",
    "available": "false",
    "song": "IWF AIO"
  },
  {
    "name": "Senia Lopez",
    "score": "82593",
    "available": "false",
    "song": "Solid Roots AIO"
  },
  {
    "name": "Barry Hendler",
    "score": "90413",
    "available": "false",
    "song": "Solid Roots AIO"
  },
  {
    "name": "Manny Perry",
    "score": "81833",
    "available": "true",
    "song": "IWF AIO"
  },
  {
    "name": "Jennifer Jakubowski",
    "score": "80718",
    "available": "false",
    "song": "Solid Roots AIO"
  },
  {
    "name": "Gary May",
    "score": "84837",
    "available": "false",
    "song": "Solid Roots AIO"
  },
  {
    "name": "Arjun Chauhan",
    "score": "84513",
    "available": "false",
    "song": "Solid Roots AIO"
  },
  {
    "name": "alaa ahmed",
    "score": "77621",
    "available": "false",
    "song": "Solid Roots AIO"
  },
  {
    "name": "Becky Katz",
    "score": "80631",
    "available": "false",
    "song": "IWF AIO"
  },
  {
    "name": "Aaron Buchanan",
    "score": "83123",
    "available": "false",
    "song": "IWF AIO"
  },
  {
    "name": "marydean czach",
    "score": "81713",
    "available": "false",
    "song": "Solid Roots AIO"
  },
  {
    "name": "Melody Mafa",
    "score": "58870",
    "available": "false",
    "song": "Solid Roots AIO"
  },
  {
    "name": "Sam Felo",
    "score": "79281",
    "available": "false",
    "song": "Solid Roots AIO"
  },
  {
    "name": "Gio Vargas",
    "score": "96469",
    "available": "false",
    "song": "Solid Roots AIO"
  },
  {
    "name": "Freddy Martinez",
    "score": "94310",
    "available": "false",
    "song": "Solid Roots AIO"
  },
  {
    "name": "Leo Martinez",
    "score": "89159",
    "available": "false",
    "song": "Solid Roots AIO"
  },
  {
    "name": "MaryDean Czach",
    "score": "80994",
    "available": "false",
    "song": "IWF AIO"
  },
  {
    "name": "Rachel Silva",
    "score": "82362",
    "available": "false",
    "song": "Solid Roots AIO"
  },
  {
    "name": "Tika Skiba",
    "score": "95907",
    "available": "false",
    "song": "Solid Roots AIO"
  },
  {
    "name": "Jim Gamrat",
    "score": "86240",
    "available": "false",
    "song": "IWF AIO"
  },
  {
    "name": "Duc",
    "score": "90653",
    "available": "false",
    "song": "Solid Roots AIO"
  },
  {
    "name": "Mike Farrell",
    "score": "91354",
    "available": "false",
    "song": "IWF AIO"
  },
  {
    "name": "Aisha Khan",
    "score": "76888",
    "available": "false",
    "song": "IWF AIO"
  },
  {
    "name": "John O'Dwyer",
    "score": "80408",
    "available": "false",
    "song": "IWF AIO"
  },
  {
    "name": "Jaclyn Fletcher",
    "score": "86569",
    "available": "false",
    "song": "IWF AIO"
  }
]
