[{"name":"admin","score":"0","available":"false","song":"Solid Roots AIO"},{"name":"Andrew Korn","score":"98348","available":"true","song":"IWF AIO"},{"name":"Jess B.","score":"93353","available":"true","song":"IWF AIO"},{"name":"MunsonCrazyMan","score":"98437","available":"true","song":"IWF AIO"},{"name":"Cook","score":"92713","available":"true","song":"Solid Roots AIO"},{"name":"Torres","score":"93595","available":"true","song":"Solid Roots AIO"},{"name":"Abe The Babe","score":"86553","available":"true","song":"Solid Roots AIO"},{"name":"Eric C.","score":"94591","available":"true","song":"IWF AIO"},{"name":"Ania","score":"83193","available":"true","song":"Solid Roots AIO"},{"name":"Tom P.","score":"93114","available":"true","song":"Solid Roots AIO"},{"name":"Niki","score":"98699","available":"true","song":"Solid Roots AIO"},{"name":"In Between Rivers","score":"96309","available":"true","song":"IWF AIO"},{"name":"Tissue","score":"98507","available":"true","song":"Solid Roots AIO"},{"name":"Devon","score":"91759","available":"false","song":"Solid Roots AIO"},{"name":"Minds","score":"87755","available":"true","song":"Solid Roots AIO"},{"name":"Noah","score":"91316","available":"false","song":"Solid Roots AIO"},{"name":"Kairi Conti","score":"90303","available":"true","song":"Solid Roots AIO"},{"name":"Abe the Babe","score":"94369","available":"true","song":"Solid Roots AIO"}]