[{"name":"Riefy RL","score":"88776","available":"false"},{"name":"Channell Diamond","score":"75164","available":"false"},{"name":"Kue","score":"62913","available":"false"},{"name":"Dappa","score":"77384","available":"false"},{"name":"Maui","score":"81872","available":"false"},{"name":"Dappa","score":"81150","available":"false"},{"name":"Glen","score":"61460","available":"true"},{"name":"Glen","score":"61460","available":"true"},{"name":"fatima conteh","score":"66318","available":"false"},{"name":"katika","score":"90168","available":"false"}]